MANIFEST.in
README.md
setup.py
pytest_agent/__init__.py
pytest_agent/__main__.py
pytest_agent/api.py
pytest_agent/commands.py
pytest_agent/controller.py
pytest_agent/database.py
pytest_agent/drivers.py
pytest_agent/dtos.py
pytest_agent/repository.py
pytest_agent/settings.py
pytest_agent.egg-info/PKG-INFO
pytest_agent.egg-info/SOURCES.txt
pytest_agent.egg-info/dependency_links.txt
pytest_agent.egg-info/entry_points.txt
pytest_agent.egg-info/requires.txt
pytest_agent.egg-info/top_level.txt
pytest_agent/static/favicon.ico
pytest_agent/static/index.html
pytest_agent/static/css/app.731a9d12.css
pytest_agent/static/css/chunk-vendors.8d33546b.css
pytest_agent/static/img/logo.c0a818de.png
pytest_agent/static/js/app.62da3902.js
pytest_agent/static/js/app.62da3902.js.map
pytest_agent/static/js/chunk-vendors.70c07ae3.js
pytest_agent/static/js/chunk-vendors.70c07ae3.js.map