Metadata-Version: 2.1
Name: pytest-agent
Version: 0.0.5
Summary: Service that exposes a REST API that can be used to interract remotely with Pytest. It is shipped with a dashboard that enables running tests in a more convenient way.
Home-page: UNKNOWN
License: UNKNOWN
Platform: UNKNOWN
